wauxio/__init__.py
wauxio/mixer.py
wauxio/output.py
wauxio/storage.py
wauxio/utils.py
wauxio/codecs/any.py
wauxio/codecs/mp3.py
wauxio-0.3.6.dist-info/METADATA
wauxio-0.3.6.dist-info/WHEEL
wauxio-0.3.6.dist-info/licenses/LICENSE
wauxio-0.3.6.dist-info/RECORD
