Metadata-Version: 2.4
Name: wauxio
Version: 0.3.6
Summary: Audio framework
Author: wumtdev
License-Expression: MIT
License-File: LICENSE
Requires-Python: >=3.12
Requires-Dist: numpy>=2.3.2
Requires-Dist: wsignals>=0.2.2
Provides-Extra: all
Requires-Dist: miniaudio>=1.61; extra == 'all'
Requires-Dist: soundfile>=0.13.1; extra == 'all'
Provides-Extra: miniaudio
Requires-Dist: miniaudio>=1.61; extra == 'miniaudio'
Provides-Extra: soundfile
Requires-Dist: soundfile>=0.13.1; extra == 'soundfile'
